Metadata-Version: 2.1
Name: flake8-simplicity
Version: 0.0.1
Summary: Take your Python syntax back to the 90s!
Home-page: https://github.com/wryun/flake8-simplicity
Author: James Haggerty
Author-email: james.haggerty@gmail.com
License: MIT
Keywords: flake8 simplicity __past__
Platform: UNKNOWN
Classifier: Development Status :: 3 - Alpha
Classifier: Framework :: Flake8
Classifier: Environment :: Console
Classifier: Intended Audience :: Developers
Classifier: License :: OSI Approved :: MIT License
Classifier: Operating System :: OS Independent
Classifier: Programming Language :: Python
Classifier: Programming Language :: Python :: 3
Classifier: Topic :: Software Development :: Libraries :: Python Modules
Classifier: Topic :: Software Development :: Quality Assurance
